uart/uart_tx.v
module uart_tx
#(parameter CLK_PER_BIT)
(
	input	clk, //obvious
	input	i_start_tx, //set to high to start transmission
	input  [7:0] i_data, // data to be transmitted
	output o_busy, // busy flag
	output o_done, // done flag
	output	reg o_tx,// bits to be transmitted
	output [1:0] o_state
	);
	reg	[7:0]	r_data;
	reg	[1:0] r_state;
	reg	[2:0]	r_bit_index;
	reg	[7:0]	r_clk_count;
	reg				r_done;
	reg				r_busy;
	parameter	s_idle	=2'b00; // wait for i_start_tx
	parameter	s_start	=2'b01; //	send start bit 
	parameter	s_trans	=2'b11; // send data
	parameter	s_end		=2'b10; //send end bit

	always @(posedge clk)
	begin
		case (r_state)
			s_idle:
				begin
					o_tx				<=1'b1;
					r_done			<=1'b1;
					r_busy			<=1'b0;
					r_bit_index	<=0;
					r_clk_count	<=0;
					r_data			<=i_data;
					if (i_start_tx==1'b1)
						begin
							r_state	<=s_start;
							r_busy	<=1'b1;
							r_done	<=1'b0;
						end else r_state <=s_idle;
				end
				s_start:
					begin
						r_done	<=1'b0;
						r_busy	<=1'b1;
						o_tx		<=1'b0;
						if (r_clk_count<CLK_PER_BIT-1)
							begin
								r_clk_count	<=r_clk_count+1;
								r_state			<=s_start;
							end else begin
									r_clk_count	<=0;
									r_state			<=s_trans;
								end
					end
					s_trans:
						begin
							o_tx	<=r_data[r_bit_index];
							if (r_clk_count<CLK_PER_BIT-1)
								begin
									r_clk_count	<=r_clk_count+1;
									r_state			<=s_trans;
								end else r_clk_count	<=0;
							if (r_clk_count<7)
								begin
									r_bit_index	<=r_bit_index+1;
									r_state			<=s_trans;
								end else begin
									r_bit_index	<=0;
									r_state			<=s_end;
								end
						end
					s_end:
						begin
							o_tx	<=1;
							if (r_clk_count<CLK_PER_BIT-1)
								begin
									r_clk_count	<=r_clk_count+1;
									r_state			<=s_end;
								end else begin
									r_done	<=1;
									r_busy	<=0;
									r_state	<=s_idle;
								end
						end
					default: r_state	<=s_idle;
		endcase
	end
		assign o_done	=r_done;
		assign o_busy	=r_busy;
		assign o_state=r_state;
	endmodule

uart/tx_tb.v
`timescale 1ns/10ps

module tx_tb ();
	parameter	c_CLK_PER_BIT		=87;

	reg clk=0;
	reg i_start_tx =0;
	reg [7:0] i_data=0;
	wire o_tx;
	wire o_done;
	wire o_busy;
	wire [1:0] o_state=0;

	always #50 clk = ~clk;

	uart_tx #(.CLK_PER_BIT(c_CLK_PER_BIT)
	) dut (
			.clk(clk),
			.i_start_tx(i_start_tx),
			.i_data(i_data),
			.o_done(o_done),
			.o_busy(o_busy),
			.o_tx(o_tx),
			.o_state(o_state)
		);

		initial begin
			$dumpfile("tx_tb.vcd");
			$dumpvars(0,tx_tb);
			i_start_tx=0;
			i_data=8'b10101011;
			#200;
			i_start_tx=1;
			#100;
			i_start_tx=0;
			wait (o_done==1);
			#200;
			$finish;
		end
endmodule

uart/tx_tb.vcd
$date
	Wed May  7 18:29:38 2025
$end
$version
	Icarus Verilog
$end
$timescale
	10ps
$end
$scope module tx_tb $end
$var wire 2 ! o_state [1:0] $end
$var wire 1 " o_tx $end
$var wire 1 # o_done $end
$var wire 1 $ o_busy $end
$var parameter 32 % c_CLK_PER_BIT $end
$var reg 1 & clk $end
$var reg 8 ' i_data [7:0] $end
$var reg 1 ( i_start_tx $end
$scope module dut $end
$var wire 1 & clk $end
$var wire 8 ) i_data [7:0] $end
$var wire 1 ( i_start_tx $end
$var wire 1 $ o_busy $end
$var wire 1 # o_done $end
$var wire 2 * o_state [1:0] $end
$var parameter 32 + CLK_PER_BIT $end
$var parameter 2 , s_end $end
$var parameter 2 - s_idle $end
$var parameter 2 . s_start $end
$var parameter 2 / s_trans $end
$var reg 1 " o_tx $end
$var reg 3 0 r_bit_index [2:0] $end
$var reg 1 1 r_busy $end
$var reg 8 2 r_clk_count [7:0] $end
$var reg 8 3 r_data [7:0] $end
$var reg 1 4 r_done $end
$var reg 2 5 r_state [1:0] $end
$upscope $end
$upscope $end
$enddefinitions $end
$comment Show the parameter values. $end
$dumpall
b11 /
b1 .
b0 -
b10 ,
b1010111 +
b1010111 %
$end
#0
$dumpvars
bx 5
x4
bx 3
bx 2
x1
bx 0
bx *
b10101011 )
0(
b10101011 '
0&
x$
x#
x"
bx !
$end
#5000
b0 !
b0 *
b0 5
1&
#10000
0&
#15000
b10101011 3
b0 2
b0 0
0$
01
1#
14
1"
1&
#20000
0&
1(
#25000
0#
04
1$
11
b0x !
b0x *
b1 5
1&
#30000
0&
0(
#35000
b1 2
0"
1&
#40000
0&
#45000
b10 2
1&
#50000
0&
#55000
b11 2
1&
#60000
0&
#65000
b100 2
1&
#70000
0&
#75000
b101 2
1&
#80000
0&
#85000
b110 2
1&
#90000
0&
#95000
b111 2
1&
#100000
0&
#105000
b1000 2
1&
#110000
0&
#115000
b1001 2
1&
#120000
0&
#125000
b1010 2
1&
#130000
0&
#135000
b1011 2
1&
#140000
0&
#145000
b1100 2
1&
#150000
0&
#155000
b1101 2
1&
#160000
0&
#165000
b1110 2
1&
#170000
0&
#175000
b1111 2
1&
#180000
0&
#185000
b10000 2
1&
#190000
0&
#195000
b10001 2
1&
#200000
0&
#205000
b10010 2
1&
#210000
0&
#215000
b10011 2
1&
#220000
0&
#225000
b10100 2
1&
#230000
0&
#235000
b10101 2
1&
#240000
0&
#245000
b10110 2
1&
#250000
0&
#255000
b10111 2
1&
#260000
0&
#265000
b11000 2
1&
#270000
0&
#275000
b11001 2
1&
#280000
0&
#285000
b11010 2
1&
#290000
0&
#295000
b11011 2
1&
#300000
0&
#305000
b11100 2
1&
#310000
0&
#315000
b11101 2
1&
#320000
0&
#325000
b11110 2
1&
#330000
0&
#335000
b11111 2
1&
#340000
0&
#345000
b100000 2
1&
#350000
0&
#355000
b100001 2
1&
#360000
0&
#365000
b100010 2
1&
#370000
0&
#375000
b100011 2
1&
#380000
0&
#385000
b100100 2
1&
#390000
0&
#395000
b100101 2
1&
#400000
0&
#405000
b100110 2
1&
#410000
0&
#415000
b100111 2
1&
#420000
0&
#425000
b101000 2
1&
#430000
0&
#435000
b101001 2
1&
#440000
0&
#445000
b101010 2
1&
#450000
0&
#455000
b101011 2
1&
#460000
0&
#465000
b101100 2
1&
#470000
0&
#475000
b101101 2
1&
#480000
0&
#485000
b101110 2
1&
#490000
0&
#495000
b101111 2
1&
#500000
0&
#505000
b110000 2
1&
#510000
0&
#515000
b110001 2
1&
#520000
0&
#525000
b110010 2
1&
#530000
0&
#535000
b110011 2
1&
#540000
0&
#545000
b110100 2
1&
#550000
0&
#555000
b110101 2
1&
#560000
0&
#565000
b110110 2
1&
#570000
0&
#575000
b110111 2
1&
#580000
0&
#585000
b111000 2
1&
#590000
0&
#595000
b111001 2
1&
#600000
0&
#605000
b111010 2
1&
#610000
0&
#615000
b111011 2
1&
#620000
0&
#625000
b111100 2
1&
#630000
0&
#635000
b111101 2
1&
#640000
0&
#645000
b111110 2
1&
#650000
0&
#655000
b111111 2
1&
#660000
0&
#665000
b1000000 2
1&
#670000
0&
#675000
b1000001 2
1&
#680000
0&
#685000
b1000010 2
1&
#690000
0&
#695000
b1000011 2
1&
#700000
0&
#705000
b1000100 2
1&
#710000
0&
#715000
b1000101 2
1&
#720000
0&
#725000
b1000110 2
1&
#730000
0&
#735000
b1000111 2
1&
#740000
0&
#745000
b1001000 2
1&
#750000
0&
#755000
b1001001 2
1&
#760000
0&
#765000
b1001010 2
1&
#770000
0&
#775000
b1001011 2
1&
#780000
0&
#785000
b1001100 2
1&
#790000
0&
#795000
b1001101 2
1&
#800000
0&
#805000
b1001110 2
1&
#810000
0&
#815000
b1001111 2
1&
#820000
0&
#825000
b1010000 2
1&
#830000
0&
#835000
b1010001 2
1&
#840000
0&
#845000
b1010010 2
1&
#850000
0&
#855000
b1010011 2
1&
#860000
0&
#865000
b1010100 2
1&
#870000
0&
#875000
b1010101 2
1&
#880000
0&
#885000
b1010110 2
1&
#890000
0&
#895000
bx !
bx *
b11 5
b0 2
1&
#900000
0&
#905000
b1 0
b1 2
1"
1&
#910000
0&
#915000
b10 0
b10 2
1&
#920000
0&
#925000
b11 0
b11 2
0"
1&
#930000
0&
#935000
b100 0
b100 2
1"
1&
#940000
0&
#945000
b101 0
b101 2
0"
1&
#950000
0&
#955000
b110 0
b110 2
1"
1&
#960000
0&
#965000
b111 0
b111 2
0"
1&
#970000
0&
#975000
bx0 !
bx0 *
b10 5
b0 0
b1000 2
1"
1&
#980000
0&
#985000
b1001 2
1&
#990000
0&
#995000
b1010 2
1&
#1000000
0&
#1005000
b1011 2
1&
#1010000
0&
#1015000
b1100 2
1&
#1020000
0&
#1025000
b1101 2
1&
#1030000
0&
#1035000
b1110 2
1&
#1040000
0&
#1045000
b1111 2
1&
#1050000
0&
#1055000
b10000 2
1&
#1060000
0&
#1065000
b10001 2
1&
#1070000
0&
#1075000
b10010 2
1&
#1080000
0&
#1085000
b10011 2
1&
#1090000
0&
#1095000
b10100 2
1&
#1100000
0&
#1105000
b10101 2
1&
#1110000
0&
#1115000
b10110 2
1&
#1120000
0&
#1125000
b10111 2
1&
#1130000
0&
#1135000
b11000 2
1&
#1140000
0&
#1145000
b11001 2
1&
#1150000
0&
#1155000
b11010 2
1&
#1160000
0&
#1165000
b11011 2
1&
#1170000
0&
#1175000
b11100 2
1&
#1180000
0&
#1185000
b11101 2
1&
#1190000
0&
#1195000
b11110 2
1&
#1200000
0&
#1205000
b11111 2
1&
#1210000
0&
#1215000
b100000 2
1&
#1220000
0&
#1225000
b100001 2
1&
#1230000
0&
#1235000
b100010 2
1&
#1240000
0&
#1245000
b100011 2
1&
#1250000
0&
#1255000
b100100 2
1&
#1260000
0&
#1265000
b100101 2
1&
#1270000
0&
#1275000
b100110 2
1&
#1280000
0&
#1285000
b100111 2
1&
#1290000
0&
#1295000
b101000 2
1&
#1300000
0&
#1305000
b101001 2
1&
#1310000
0&
#1315000
b101010 2
1&
#1320000
0&
#1325000
b101011 2
1&
#1330000
0&
#1335000
b101100 2
1&
#1340000
0&
#1345000
b101101 2
1&
#1350000
0&
#1355000
b101110 2
1&
#1360000
0&
#1365000
b101111 2
1&
#1370000
0&
#1375000
b110000 2
1&
#1380000
0&
#1385000
b110001 2
1&
#1390000
0&
#1395000
b110010 2
1&
#1400000
0&
#1405000
b110011 2
1&
#1410000
0&
#1415000
b110100 2
1&
#1420000
0&
#1425000
b110101 2
1&
#1430000
0&
#1435000
b110110 2
1&
#1440000
0&
#1445000
b110111 2
1&
#1450000
0&
#1455000
b111000 2
1&
#1460000
0&
#1465000
b111001 2
1&
#1470000
0&
#1475000
b111010 2
1&
#1480000
0&
#1485000
b111011 2
1&
#1490000
0&
#1495000
b111100 2
1&
#1500000
0&
#1505000
b111101 2
1&
#1510000
0&
#1515000
b111110 2
1&
#1520000
0&
#1525000
b111111 2
1&
#1530000
0&
#1535000
b1000000 2
1&
#1540000
0&
#1545000
b1000001 2
1&
#1550000
0&
#1555000
b1000010 2
1&
#1560000
0&
#1565000
b1000011 2
1&
#1570000
0&
#1575000
b1000100 2
1&
#1580000
0&
#1585000
b1000101 2
1&
#1590000
0&
#1595000
b1000110 2
1&
#1600000
0&
#1605000
b1000111 2
1&
#1610000
0&
#1615000
b1001000 2
1&
#1620000
0&
#1625000
b1001001 2
1&
#1630000
0&
#1635000
b1001010 2
1&
#1640000
0&
#1645000
b1001011 2
1&
#1650000
0&
#1655000
b1001100 2
1&
#1660000
0&
#1665000
b1001101 2
1&
#1670000
0&
#1675000
b1001110 2
1&
#1680000
0&
#1685000
b1001111 2
1&
#1690000
0&
#1695000
b1010000 2
1&
#1700000
0&
#1705000
b1010001 2
1&
#1710000
0&
#1715000
b1010010 2
1&
#1720000
0&
#1725000
b1010011 2
1&
#1730000
0&
#1735000
b1010100 2
1&
#1740000
0&
#1745000
b1010101 2
1&
#1750000
0&
#1755000
b1010110 2
1&
#1760000
0&
#1765000
b0 !
b0 *
b0 5
0$
01
1#
14
1&
#1770000
0&
#1775000
b0 2
1&
