uart/uart_rx.v
module uart_rx
#(parameter CLK_PER_BIT)
(
	input clk,
	input i_rx,
	output [7:0] o_data,
	output o_done
	);
	reg r_incoming;
	reg r_rx;
	reg r_done;
	reg [7:0] r_data;
	reg [7:0] r_clk_count;
	reg [2:0] r_bit_index;
	reg [1:0] r_state;
	localparam s_idle=2'b00;
	localparam s_start=2'b01;
	localparam s_recieve=2'b11;
	localparam s_stop=2'b10;

	//fix metastability issues
	always @(posedge clk) begin
		r_incoming <= i_rx;
		r_rx <= r_incoming;
	end

	//state machine
	always @(posedge clk) begin
		case (r_state)
			s_idle:
				begin
					r_done <= 1;
					r_state <= s_idle;
					r_clk_count <= 0;
					r_bit_index <= 0;
					if (~r_rx)
						begin
							r_state <= s_start;
							r_done <= 0;
						end else r_state <= s_idle;
					end
			s_start:
				begin
					if (r_clk_count==((CLK_PER_BIT-1)/2))
						begin
							if (r_rx) r_state <= s_idle;
							else begin
								r_state <= s_recieve;
								r_clk_count <= 0;
							end
						end else begin
							r_clk_count <= r_clk_count+1;
							r_state <= s_start;
						end
				end
			s_recieve:
				begin
					if (r_clk_count==(CLK_PER_BIT-1))
						begin
							r_data[r_bit_index] <= r_rx;
							r_clk_count <= 0;
							r_bit_index	<= r_bit_index+1;
							if (r_bit_index == 7) r_state <= s_stop;
						end else begin
							r_clk_count <= r_clk_count+1;
							r_state <= s_recieve;
							end
				end 
			s_stop:
				begin
					if (r_clk_count==(CLK_PER_BIT-1))
						begin
							r_clk_count <= 0;
							if (r_rx == 1)
								begin
									r_state <= s_idle;
								end
							end else begin
								r_clk_count <= r_clk_count+1;
								r_state <= s_stop;
								end
				end
			default: r_state<=s_idle;
		endcase
	end

	//ouputs
	assign o_done = r_done;
	assign o_data = r_data;
endmodule

uart/uart_tx.v
module uart_tx
#(parameter CLK_PER_BIT)
(
	input	clk, //obvious
	input	i_start_tx, //set to high to start transmission
	input  [7:0] i_data, // data to be transmitted
	output o_busy, // busy flag
	output o_done, // done flag
	output	reg o_tx// bits to be transmitted
	);
	reg	[7:0]	r_data;
	reg	[1:0] r_state;
	reg	[2:0]	r_bit_index;
	reg	[7:0]	r_clk_count;
	reg				r_done;
	reg				r_busy;
	localparam	s_idle	=2'b00; // wait for i_start_tx
	localparam	s_start	=2'b01; //	send start bit 
	localparam	s_trans	=2'b11; // send data
	localparam	s_end		=2'b10; //send end bit

	always @(posedge clk)
	begin
		case (r_state)
			s_idle:
				begin
					o_tx				<=1'b1;
					r_done			<=1'b1;
					r_busy			<=1'b0;
					r_bit_index	<=0;
					r_clk_count	<=0;
					r_data			<=i_data;
					if (i_start_tx==1'b1)
						begin
							r_state	<=s_start;
							r_busy	<=1'b1;
							r_done	<=1'b0;
						end else r_state <=s_idle;
				end
				s_start:
					begin
						r_done	<=1'b0;
						r_busy	<=1'b1;
						o_tx		<=1'b0;
						if (r_clk_count<CLK_PER_BIT-1)
							begin
								r_clk_count	<=r_clk_count+1;
								r_state			<=s_start;
							end else begin
									r_clk_count	<=0;
									r_state			<=s_trans;
									r_clk_count	<=0;
								end
					end
					s_trans:
						begin
							r_done	<=1'b0;
							r_busy	<=1'b1;
							o_tx	<=r_data[r_bit_index];
							if (r_clk_count<CLK_PER_BIT-1)
								begin
									r_clk_count	<=r_clk_count+1;
									r_state			<=s_trans;
								end else begin
									r_clk_count	<=0;
									if (r_bit_index<7)
										begin
											r_bit_index	<=r_bit_index+1;
											r_state			<=s_trans;
										end else begin
											r_bit_index	<=0;
											r_state			<=s_end;
											r_clk_count	<=0;
										end
								end
						end
					s_end:
						begin
							o_tx	<=1;
							if (r_clk_count<CLK_PER_BIT-1)
								begin
									r_clk_count	<=r_clk_count+1;
									r_state			<=s_end;
								end else begin
									r_done	<=1;
									r_busy	<=0;
									r_state	<=s_idle;
									r_clk_count	<=0;
								end
						end
					default: r_state	<=s_idle;
		endcase
	end
		assign o_done	=r_done;
		assign o_busy	=r_busy;
	endmodule

uart/uart_tb.v
`timescale 1ns/10ps

module uart_tb ();
	parameter	c_CLK_PER_BIT		=87;

	reg clk=0;
	reg i_start_tx =0;
	reg [7:0] i_data=0;
	wire o_tx;
	wire o_tx_done;
	wire o_tx_busy;
	wire o_rx_done;
	wire [7:0] o_rx_data;

	always #50 clk = ~clk;

	uart_tx #(.CLK_PER_BIT(c_CLK_PER_BIT)
	) dut_tx (
			.clk(clk),
			.i_start_tx(i_start_tx),
			.i_data(i_data),
			.o_done(o_tx_done),
			.o_busy(o_tx_busy),
			.o_tx(o_tx)
		);

	uart_rx #(.CLK_PER_BIT(c_CLK_PER_BIT)
	) dut_rx (
			.clk(clk),
			.i_rx(o_tx),
			.o_data(o_rx_data),
			.o_done(o_rx_done)
		);

		initial begin
			$dumpfile("uart_tb.vcd");
			$dumpvars(0,uart_tb);
			i_start_tx=0;
			i_data=8'b10101011;
			#200;
			i_start_tx=1;
			#100;
			i_start_tx=0;
			wait (o_tx_done==1);
			wait (o_rx_done==1);
			#200;
			$finish;
		end
endmodule

uart/uart_tb.vcd
$date
	Thu May  8 14:27:56 2025
$end
$version
	Icarus Verilog
$end
$timescale
	10ps
$end
$scope module uart_tb $end
$var wire 1 ! o_tx_done $end
$var wire 1 " o_tx_busy $end
$var wire 1 # o_tx $end
$var wire 1 $ o_rx_done $end
$var wire 8 % o_rx_data [7:0] $end
$var parameter 32 & c_CLK_PER_BIT $end
$var reg 1 ' clk $end
$var reg 8 ( i_data [7:0] $end
$var reg 1 ) i_start_tx $end
$scope module dut_rx $end
$var wire 1 ' clk $end
$var wire 8 * o_data [7:0] $end
$var wire 1 $ o_done $end
$var wire 1 # i_rx $end
$var parameter 32 + CLK_PER_BIT $end
$var parameter 2 , s_idle $end
$var parameter 2 - s_recieve $end
$var parameter 2 . s_start $end
$var parameter 2 / s_stop $end
$var reg 3 0 r_bit_index [2:0] $end
$var reg 8 1 r_clk_count [7:0] $end
$var reg 8 2 r_data [7:0] $end
$var reg 1 3 r_done $end
$var reg 1 4 r_incoming $end
$var reg 1 5 r_rx $end
$var reg 2 6 r_state [1:0] $end
$upscope $end
$scope module dut_tx $end
$var wire 1 ' clk $end
$var wire 8 7 i_data [7:0] $end
$var wire 1 ) i_start_tx $end
$var wire 1 " o_busy $end
$var wire 1 ! o_done $end
$var parameter 32 8 CLK_PER_BIT $end
$var parameter 2 9 s_end $end
$var parameter 2 : s_idle $end
$var parameter 2 ; s_start $end
$var parameter 2 < s_trans $end
$var reg 1 # o_tx $end
$var reg 3 = r_bit_index [2:0] $end
$var reg 1 > r_busy $end
$var reg 8 ? r_clk_count [7:0] $end
$var reg 8 @ r_data [7:0] $end
$var reg 1 A r_done $end
$var reg 2 B r_state [1:0] $end
$upscope $end
$upscope $end
$enddefinitions $end
$comment Show the parameter values. $end
$dumpall
b11 <
b1 ;
b0 :
b10 9
b1010111 8
b10 /
b1 .
b11 -
b0 ,
b1010111 +
b1010111 &
$end
#0
$dumpvars
bx B
xA
bx @
bx ?
x>
bx =
b10101011 7
bx 6
x5
x4
x3
bx 2
bx 1
bx 0
bx *
0)
b10101011 (
0'
bx %
x$
x#
x"
x!
$end
#5000
b0 B
b0 6
1'
#10000
0'
#15000
b0 0
b0 1
1$
13
b10101011 @
b0 ?
b0 =
0"
0>
1!
1A
1#
1'
#20000
0'
1)
#25000
0!
0A
1"
1>
b1 B
14
1'
#30000
0'
0)
#35000
15
b1 ?
0#
1'
#40000
0'
#45000
b10 ?
04
1'
#50000
0'
#55000
05
b11 ?
1'
#60000
0'
#65000
b100 ?
0$
03
b1 6
1'
#70000
0'
#75000
b1 1
b101 ?
1'
#80000
0'
#85000
b110 ?
b10 1
1'
#90000
0'
#95000
b11 1
b111 ?
1'
#100000
0'
#105000
b1000 ?
b100 1
1'
#110000
0'
#115000
b101 1
b1001 ?
1'
#120000
0'
#125000
b1010 ?
b110 1
1'
#130000
0'
#135000
b111 1
b1011 ?
1'
#140000
0'
#145000
b1100 ?
b1000 1
1'
#150000
0'
#155000
b1001 1
b1101 ?
1'
#160000
0'
#165000
b1110 ?
b1010 1
1'
#170000
0'
#175000
b1011 1
b1111 ?
1'
#180000
0'
#185000
b10000 ?
b1100 1
1'
#190000
0'
#195000
b1101 1
b10001 ?
1'
#200000
0'
#205000
b10010 ?
b1110 1
1'
#210000
0'
#215000
b1111 1
b10011 ?
1'
#220000
0'
#225000
b10100 ?
b10000 1
1'
#230000
0'
#235000
b10001 1
b10101 ?
1'
#240000
0'
#245000
b10110 ?
b10010 1
1'
#250000
0'
#255000
b10011 1
b10111 ?
1'
#260000
0'
#265000
b11000 ?
b10100 1
1'
#270000
0'
#275000
b10101 1
b11001 ?
1'
#280000
0'
#285000
b11010 ?
b10110 1
1'
#290000
0'
#295000
b10111 1
b11011 ?
1'
#300000
0'
#305000
b11100 ?
b11000 1
1'
#310000
0'
#315000
b11001 1
b11101 ?
1'
#320000
0'
#325000
b11110 ?
b11010 1
1'
#330000
0'
#335000
b11011 1
b11111 ?
1'
#340000
0'
#345000
b100000 ?
b11100 1
1'
#350000
0'
#355000
b11101 1
b100001 ?
1'
#360000
0'
#365000
b100010 ?
b11110 1
1'
#370000
0'
#375000
b11111 1
b100011 ?
1'
#380000
0'
#385000
b100100 ?
b100000 1
1'
#390000
0'
#395000
b100001 1
b100101 ?
1'
#400000
0'
#405000
b100110 ?
b100010 1
1'
#410000
0'
#415000
b100011 1
b100111 ?
1'
#420000
0'
#425000
b101000 ?
b100100 1
1'
#430000
0'
#435000
b100101 1
b101001 ?
1'
#440000
0'
#445000
b101010 ?
b100110 1
1'
#450000
0'
#455000
b100111 1
b101011 ?
1'
#460000
0'
#465000
b101100 ?
b101000 1
1'
#470000
0'
#475000
b101001 1
b101101 ?
1'
#480000
0'
#485000
b101110 ?
b101010 1
1'
#490000
0'
#495000
b101011 1
b101111 ?
1'
#500000
0'
#505000
b110000 ?
b0 1
b11 6
1'
#510000
0'
#515000
b1 1
b110001 ?
1'
#520000
0'
#525000
b110010 ?
b10 1
1'
#530000
0'
#535000
b11 1
b110011 ?
1'
#540000
0'
#545000
b110100 ?
b100 1
1'
#550000
0'
#555000
b101 1
b110101 ?
1'
#560000
0'
#565000
b110110 ?
b110 1
1'
#570000
0'
#575000
b111 1
b110111 ?
1'
#580000
0'
#585000
b111000 ?
b1000 1
1'
#590000
0'
#595000
b1001 1
b111001 ?
1'
#600000
0'
#605000
b111010 ?
b1010 1
1'
#610000
0'
#615000
b1011 1
b111011 ?
1'
#620000
0'
#625000
b111100 ?
b1100 1
1'
#630000
0'
#635000
b1101 1
b111101 ?
1'
#640000
0'
#645000
b111110 ?
b1110 1
1'
#650000
0'
#655000
b1111 1
b111111 ?
1'
#660000
0'
#665000
b1000000 ?
b10000 1
1'
#670000
0'
#675000
b10001 1
b1000001 ?
1'
#680000
0'
#685000
b1000010 ?
b10010 1
1'
#690000
0'
#695000
b10011 1
b1000011 ?
1'
#700000
0'
#705000
b1000100 ?
b10100 1
1'
#710000
0'
#715000
b10101 1
b1000101 ?
1'
#720000
0'
#725000
b1000110 ?
b10110 1
1'
#730000
0'
#735000
b10111 1
b1000111 ?
1'
#740000
0'
#745000
b1001000 ?
b11000 1
1'
#750000
0'
#755000
b11001 1
b1001001 ?
1'
#760000
0'
#765000
b1001010 ?
b11010 1
1'
#770000
0'
#775000
b11011 1
b1001011 ?
1'
#780000
0'
#785000
b1001100 ?
b11100 1
1'
#790000
0'
#795000
b11101 1
b1001101 ?
1'
#800000
0'
#805000
b1001110 ?
b11110 1
1'
#810000
0'
#815000
b11111 1
b1001111 ?
1'
#820000
0'
#825000
b1010000 ?
b100000 1
1'
#830000
0'
#835000
b100001 1
b1010001 ?
1'
#840000
0'
#845000
b1010010 ?
b100010 1
1'
#850000
0'
#855000
b100011 1
b1010011 ?
1'
#860000
0'
#865000
b1010100 ?
b100100 1
1'
#870000
0'
#875000
b100101 1
b1010101 ?
1'
#880000
0'
#885000
b1010110 ?
b100110 1
1'
#890000
0'
#895000
b100111 1
b11 B
b0 ?
1'
#900000
0'
#905000
b1 ?
1#
b101000 1
1'
#910000
0'
#915000
b101001 1
14
b10 ?
1'
#920000
0'
#925000
b11 ?
15
b101010 1
1'
#930000
0'
#935000
b101011 1
b100 ?
1'
#940000
0'
#945000
b101 ?
b101100 1
1'
#950000
0'
#955000
b101101 1
b110 ?
1'
#960000
0'
#965000
b111 ?
b101110 1
1'
#970000
0'
#975000
b101111 1
b1000 ?
1'
#980000
0'
#985000
b1001 ?
b110000 1
1'
#990000
0'
#995000
b110001 1
b1010 ?
1'
#1000000
0'
#1005000
b1011 ?
b110010 1
1'
#1010000
0'
#1015000
b110011 1
b1100 ?
1'
#1020000
0'
#1025000
b1101 ?
b110100 1
1'
#1030000
0'
#1035000
b110101 1
b1110 ?
1'
#1040000
0'
#1045000
b1111 ?
b110110 1
1'
#1050000
0'
#1055000
b110111 1
b10000 ?
1'
#1060000
0'
#1065000
b10001 ?
b111000 1
1'
#1070000
0'
#1075000
b111001 1
b10010 ?
1'
#1080000
0'
#1085000
b10011 ?
b111010 1
1'
#1090000
0'
#1095000
b111011 1
b10100 ?
1'
#1100000
0'
#1105000
b10101 ?
b111100 1
1'
#1110000
0'
#1115000
b111101 1
b10110 ?
1'
#1120000
0'
#1125000
b10111 ?
b111110 1
1'
#1130000
0'
#1135000
b111111 1
b11000 ?
1'
#1140000
0'
#1145000
b11001 ?
b1000000 1
1'
#1150000
0'
#1155000
b1000001 1
b11010 ?
1'
#1160000
0'
#1165000
b11011 ?
b1000010 1
1'
#1170000
0'
#1175000
b1000011 1
b11100 ?
1'
#1180000
0'
#1185000
b11101 ?
b1000100 1
1'
#1190000
0'
#1195000
b1000101 1
b11110 ?
1'
#1200000
0'
#1205000
b11111 ?
b1000110 1
1'
#1210000
0'
#1215000
b1000111 1
b100000 ?
1'
#1220000
0'
#1225000
b100001 ?
b1001000 1
1'
#1230000
0'
#1235000
b1001001 1
b100010 ?
1'
#1240000
0'
#1245000
b100011 ?
b1001010 1
1'
#1250000
0'
#1255000
b1001011 1
b100100 ?
1'
#1260000
0'
#1265000
b100101 ?
b1001100 1
1'
#1270000
0'
#1275000
b1001101 1
b100110 ?
1'
#1280000
0'
#1285000
b100111 ?
b1001110 1
1'
#1290000
0'
#1295000
b1001111 1
b101000 ?
1'
#1300000
0'
#1305000
b101001 ?
b1010000 1
1'
#1310000
0'
#1315000
b1010001 1
b101010 ?
1'
#1320000
0'
#1325000
b101011 ?
b1010010 1
1'
#1330000
0'
#1335000
b1010011 1
b101100 ?
1'
#1340000
0'
#1345000
b101101 ?
b1010100 1
1'
#1350000
0'
#1355000
b1010101 1
b101110 ?
1'
#1360000
0'
#1365000
b101111 ?
b1010110 1
1'
#1370000
0'
#1375000
b1 0
b0 1
bx1 %
bx1 *
bx1 2
b110000 ?
1'
#1380000
0'
#1385000
b110001 ?
b1 1
1'
#1390000
0'
#1395000
b10 1
b110010 ?
1'
#1400000
0'
#1405000
b110011 ?
b11 1
1'
#1410000
0'
#1415000
b100 1
b110100 ?
1'
#1420000
0'
#1425000
b110101 ?
b101 1
1'
#1430000
0'
#1435000
b110 1
b110110 ?
1'
#1440000
0'
#1445000
b110111 ?
b111 1
1'
#1450000
0'
#1455000
b1000 1
b111000 ?
1'
#1460000
0'
#1465000
b111001 ?
b1001 1
1'
#1470000
0'
#1475000
b1010 1
b111010 ?
1'
#1480000
0'
#1485000
b111011 ?
b1011 1
1'
#1490000
0'
#1495000
b1100 1
b111100 ?
1'
#1500000
0'
#1505000
b111101 ?
b1101 1
1'
#1510000
0'
#1515000
b1110 1
b111110 ?
1'
#1520000
0'
#1525000
b111111 ?
b1111 1
1'
#1530000
0'
#1535000
b10000 1
b1000000 ?
1'
#1540000
0'
#1545000
b1000001 ?
b10001 1
1'
#1550000
0'
#1555000
b10010 1
b1000010 ?
1'
#1560000
0'
#1565000
b1000011 ?
b10011 1
1'
#1570000
0'
#1575000
b10100 1
b1000100 ?
1'
#1580000
0'
#1585000
b1000101 ?
b10101 1
1'
#1590000
0'
#1595000
b10110 1
b1000110 ?
1'
#1600000
0'
#1605000
b1000111 ?
b10111 1
1'
#1610000
0'
#1615000
b11000 1
b1001000 ?
1'
#1620000
0'
#1625000
b1001001 ?
b11001 1
1'
#1630000
0'
#1635000
b11010 1
b1001010 ?
1'
#1640000
0'
#1645000
b1001011 ?
b11011 1
1'
#1650000
0'
#1655000
b11100 1
b1001100 ?
1'
#1660000
0'
#1665000
b1001101 ?
b11101 1
1'
#1670000
0'
#1675000
b11110 1
b1001110 ?
1'
#1680000
0'
#1685000
b1001111 ?
b11111 1
1'
#1690000
0'
#1695000
b100000 1
b1010000 ?
1'
#1700000
0'
#1705000
b1010001 ?
b100001 1
1'
#1710000
0'
#1715000
b100010 1
b1010010 ?
1'
#1720000
0'
#1725000
b1010011 ?
b100011 1
1'
#1730000
0'
#1735000
b100100 1
b1010100 ?
1'
#1740000
0'
#1745000
b1010101 ?
b100101 1
1'
#1750000
0'
#1755000
b100110 1
b1010110 ?
1'
#1760000
0'
#1765000
b1 =
b0 ?
b100111 1
1'
#1770000
0'
#1775000
b101000 1
b1 ?
1'
#1780000
0'
#1785000
b10 ?
b101001 1
1'
#1790000
0'
#1795000
b101010 1
b11 ?
1'
#1800000
0'
#1805000
b100 ?
b101011 1
1'
#1810000
0'
#1815000
b101100 1
b101 ?
1'
#1820000
0'
#1825000
b110 ?
b101101 1
1'
#1830000
0'
#1835000
b101110 1
b111 ?
1'
#1840000
0'
#1845000
b1000 ?
b101111 1
1'
#1850000
0'
#1855000
b110000 1
b1001 ?
1'
#1860000
0'
#1865000
b1010 ?
b110001 1
1'
#1870000
0'
#1875000
b110010 1
b1011 ?
1'
#1880000
0'
#1885000
b1100 ?
b110011 1
1'
#1890000
0'
#1895000
b110100 1
b1101 ?
1'
#1900000
0'
#1905000
b1110 ?
b110101 1
1'
#1910000
0'
#1915000
b110110 1
b1111 ?
1'
#1920000
0'
#1925000
b10000 ?
b110111 1
1'
#1930000
0'
#1935000
b111000 1
b10001 ?
1'
#1940000
0'
#1945000
b10010 ?
b111001 1
1'
#1950000
0'
#1955000
b111010 1
b10011 ?
1'
#1960000
0'
#1965000
b10100 ?
b111011 1
1'
#1970000
0'
#1975000
b111100 1
b10101 ?
1'
#1980000
0'
#1985000
b10110 ?
b111101 1
1'
#1990000
0'
#1995000
b111110 1
b10111 ?
1'
#2000000
0'
#2005000
b11000 ?
b111111 1
1'
#2010000
0'
#2015000
b1000000 1
b11001 ?
1'
#2020000
0'
#2025000
b11010 ?
b1000001 1
1'
#2030000
0'
#2035000
b1000010 1
b11011 ?
1'
#2040000
0'
#2045000
b11100 ?
b1000011 1
1'
#2050000
0'
#2055000
b1000100 1
b11101 ?
1'
#2060000
0'
#2065000
b11110 ?
b1000101 1
1'
#2070000
0'
#2075000
b1000110 1
b11111 ?
1'
#2080000
0'
#2085000
b100000 ?
b1000111 1
1'
#2090000
0'
#2095000
b1001000 1
b100001 ?
1'
#2100000
0'
#2105000
b100010 ?
b1001001 1
1'
#2110000
0'
#2115000
b1001010 1
b100011 ?
1'
#2120000
0'
#2125000
b100100 ?
b1001011 1
1'
#2130000
0'
#2135000
b1001100 1
b100101 ?
1'
#2140000
0'
#2145000
b100110 ?
b1001101 1
1'
#2150000
0'
#2155000
b1001110 1
b100111 ?
1'
#2160000
0'
#2165000
b101000 ?
b1001111 1
1'
#2170000
0'
#2175000
b1010000 1
b101001 ?
1'
#2180000
0'
#2185000
b101010 ?
b1010001 1
1'
#2190000
0'
#2195000
b1010010 1
b101011 ?
1'
#2200000
0'
#2205000
b101100 ?
b1010011 1
1'
#2210000
0'
#2215000
b1010100 1
b101101 ?
1'
#2220000
0'
#2225000
b101110 ?
b1010101 1
1'
#2230000
0'
#2235000
b1010110 1
b101111 ?
1'
#2240000
0'
#2245000
b110000 ?
b10 0
b0 1
bx11 %
bx11 *
bx11 2
1'
#2250000
0'
#2255000
b1 1
b110001 ?
1'
#2260000
0'
#2265000
b110010 ?
b10 1
1'
#2270000
0'
#2275000
b11 1
b110011 ?
1'
#2280000
0'
#2285000
b110100 ?
b100 1
1'
#2290000
0'
#2295000
b101 1
b110101 ?
1'
#2300000
0'
#2305000
b110110 ?
b110 1
1'
#2310000
0'
#2315000
b111 1
b110111 ?
1'
#2320000
0'
#2325000
b111000 ?
b1000 1
1'
#2330000
0'
#2335000
b1001 1
b111001 ?
1'
#2340000
0'
#2345000
b111010 ?
b1010 1
1'
#2350000
0'
#2355000
b1011 1
b111011 ?
1'
#2360000
0'
#2365000
b111100 ?
b1100 1
1'
#2370000
0'
#2375000
b1101 1
b111101 ?
1'
#2380000
0'
#2385000
b111110 ?
b1110 1
1'
#2390000
0'
#2395000
b1111 1
b111111 ?
1'
#2400000
0'
#2405000
b1000000 ?
b10000 1
1'
#2410000
0'
#2415000
b10001 1
b1000001 ?
1'
#2420000
0'
#2425000
b1000010 ?
b10010 1
1'
#2430000
0'
#2435000
b10011 1
b1000011 ?
1'
#2440000
0'
#2445000
b1000100 ?
b10100 1
1'
#2450000
0'
#2455000
b10101 1
b1000101 ?
1'
#2460000
0'
#2465000
b1000110 ?
b10110 1
1'
#2470000
0'
#2475000
b10111 1
b1000111 ?
1'
#2480000
0'
#2485000
b1001000 ?
b11000 1
1'
#2490000
0'
#2495000
b11001 1
b1001001 ?
1'
#2500000
0'
#2505000
b1001010 ?
b11010 1
1'
#2510000
0'
#2515000
b11011 1
b1001011 ?
1'
#2520000
0'
#2525000
b1001100 ?
b11100 1
1'
#2530000
0'
#2535000
b11101 1
b1001101 ?
1'
#2540000
0'
#2545000
b1001110 ?
b11110 1
1'
#2550000
0'
#2555000
b11111 1
b1001111 ?
1'
#2560000
0'
#2565000
b1010000 ?
b100000 1
1'
#2570000
0'
#2575000
b100001 1
b1010001 ?
1'
#2580000
0'
#2585000
b1010010 ?
b100010 1
1'
#2590000
0'
#2595000
b100011 1
b1010011 ?
1'
#2600000
0'
#2605000
b1010100 ?
b100100 1
1'
#2610000
0'
#2615000
b100101 1
b1010101 ?
1'
#2620000
0'
#2625000
b1010110 ?
b100110 1
1'
#2630000
0'
#2635000
b100111 1
b10 =
b0 ?
1'
#2640000
0'
#2645000
b1 ?
0#
b101000 1
1'
#2650000
0'
#2655000
b101001 1
04
b10 ?
1'
#2660000
0'
#2665000
b11 ?
05
b101010 1
1'
#2670000
0'
#2675000
b101011 1
b100 ?
1'
#2680000
0'
#2685000
b101 ?
b101100 1
1'
#2690000
0'
#2695000
b101101 1
b110 ?
1'
#2700000
0'
#2705000
b111 ?
b101110 1
1'
#2710000
0'
#2715000
b101111 1
b1000 ?
1'
#2720000
0'
#2725000
b1001 ?
b110000 1
1'
#2730000
0'
#2735000
b110001 1
b1010 ?
1'
#2740000
0'
#2745000
b1011 ?
b110010 1
1'
#2750000
0'
#2755000
b110011 1
b1100 ?
1'
#2760000
0'
#2765000
b1101 ?
b110100 1
1'
#2770000
0'
#2775000
b110101 1
b1110 ?
1'
#2780000
0'
#2785000
b1111 ?
b110110 1
1'
#2790000
0'
#2795000
b110111 1
b10000 ?
1'
#2800000
0'
#2805000
b10001 ?
b111000 1
1'
#2810000
0'
#2815000
b111001 1
b10010 ?
1'
#2820000
0'
#2825000
b10011 ?
b111010 1
1'
#2830000
0'
#2835000
b111011 1
b10100 ?
1'
#2840000
0'
#2845000
b10101 ?
b111100 1
1'
#2850000
0'
#2855000
b111101 1
b10110 ?
1'
#2860000
0'
#2865000
b10111 ?
b111110 1
1'
#2870000
0'
#2875000
b111111 1
b11000 ?
1'
#2880000
0'
#2885000
b11001 ?
b1000000 1
1'
#2890000
0'
#2895000
b1000001 1
b11010 ?
1'
#2900000
0'
#2905000
b11011 ?
b1000010 1
1'
#2910000
0'
#2915000
b1000011 1
b11100 ?
1'
#2920000
0'
#2925000
b11101 ?
b1000100 1
1'
#2930000
0'
#2935000
b1000101 1
b11110 ?
1'
#2940000
0'
#2945000
b11111 ?
b1000110 1
1'
#2950000
0'
#2955000
b1000111 1
b100000 ?
1'
#2960000
0'
#2965000
b100001 ?
b1001000 1
1'
#2970000
0'
#2975000
b1001001 1
b100010 ?
1'
#2980000
0'
#2985000
b100011 ?
b1001010 1
1'
#2990000
0'
#2995000
b1001011 1
b100100 ?
1'
#3000000
0'
#3005000
b100101 ?
b1001100 1
1'
#3010000
0'
#3015000
b1001101 1
b100110 ?
1'
#3020000
0'
#3025000
b100111 ?
b1001110 1
1'
#3030000
0'
#3035000
b1001111 1
b101000 ?
1'
#3040000
0'
#3045000
b101001 ?
b1010000 1
1'
#3050000
0'
#3055000
b1010001 1
b101010 ?
1'
#3060000
0'
#3065000
b101011 ?
b1010010 1
1'
#3070000
0'
#3075000
b1010011 1
b101100 ?
1'
#3080000
0'
#3085000
b101101 ?
b1010100 1
1'
#3090000
0'
#3095000
b1010101 1
b101110 ?
1'
#3100000
0'
#3105000
b101111 ?
b1010110 1
1'
#3110000
0'
#3115000
b11 0
b0 1
bx011 %
bx011 *
bx011 2
b110000 ?
1'
#3120000
0'
#3125000
b110001 ?
b1 1
1'
#3130000
0'
#3135000
b10 1
b110010 ?
1'
#3140000
0'
#3145000
b110011 ?
b11 1
1'
#3150000
0'
#3155000
b100 1
b110100 ?
1'
#3160000
0'
#3165000
b110101 ?
b101 1
1'
#3170000
0'
#3175000
b110 1
b110110 ?
1'
#3180000
0'
#3185000
b110111 ?
b111 1
1'
#3190000
0'
#3195000
b1000 1
b111000 ?
1'
#3200000
0'
#3205000
b111001 ?
b1001 1
1'
#3210000
0'
#3215000
b1010 1
b111010 ?
1'
#3220000
0'
#3225000
b111011 ?
b1011 1
1'
#3230000
0'
#3235000
b1100 1
b111100 ?
1'
#3240000
0'
#3245000
b111101 ?
b1101 1
1'
#3250000
0'
#3255000
b1110 1
b111110 ?
1'
#3260000
0'
#3265000
b111111 ?
b1111 1
1'
#3270000
0'
#3275000
b10000 1
b1000000 ?
1'
#3280000
0'
#3285000
b1000001 ?
b10001 1
1'
#3290000
0'
#3295000
b10010 1
b1000010 ?
1'
#3300000
0'
#3305000
b1000011 ?
b10011 1
1'
#3310000
0'
#3315000
b10100 1
b1000100 ?
1'
#3320000
0'
#3325000
b1000101 ?
b10101 1
1'
#3330000
0'
#3335000
b10110 1
b1000110 ?
1'
#3340000
0'
#3345000
b1000111 ?
b10111 1
1'
#3350000
0'
#3355000
b11000 1
b1001000 ?
1'
#3360000
0'
#3365000
b1001001 ?
b11001 1
1'
#3370000
0'
#3375000
b11010 1
b1001010 ?
1'
#3380000
0'
#3385000
b1001011 ?
b11011 1
1'
#3390000
0'
#3395000
b11100 1
b1001100 ?
1'
#3400000
0'
#3405000
b1001101 ?
b11101 1
1'
#3410000
0'
#3415000
b11110 1
b1001110 ?
1'
#3420000
0'
#3425000
b1001111 ?
b11111 1
1'
#3430000
0'
#3435000
b100000 1
b1010000 ?
1'
#3440000
0'
#3445000
b1010001 ?
b100001 1
1'
#3450000
0'
#3455000
b100010 1
b1010010 ?
1'
#3460000
0'
#3465000
b1010011 ?
b100011 1
1'
#3470000
0'
#3475000
b100100 1
b1010100 ?
1'
#3480000
0'
#3485000
b1010101 ?
b100101 1
1'
#3490000
0'
#3495000
b100110 1
b1010110 ?
1'
#3500000
0'
#3505000
b11 =
b0 ?
b100111 1
1'
#3510000
0'
#3515000
b101000 1
b1 ?
1#
1'
#3520000
0'
#3525000
b10 ?
14
b101001 1
1'
#3530000
0'
#3535000
b101010 1
15
b11 ?
1'
#3540000
0'
#3545000
b100 ?
b101011 1
1'
#3550000
0'
#3555000
b101100 1
b101 ?
1'
#3560000
0'
#3565000
b110 ?
b101101 1
1'
#3570000
0'
#3575000
b101110 1
b111 ?
1'
#3580000
0'
#3585000
b1000 ?
b101111 1
1'
#3590000
0'
#3595000
b110000 1
b1001 ?
1'
#3600000
0'
#3605000
b1010 ?
b110001 1
1'
#3610000
0'
#3615000
b110010 1
b1011 ?
1'
#3620000
0'
#3625000
b1100 ?
b110011 1
1'
#3630000
0'
#3635000
b110100 1
b1101 ?
1'
#3640000
0'
#3645000
b1110 ?
b110101 1
1'
#3650000
0'
#3655000
b110110 1
b1111 ?
1'
#3660000
0'
#3665000
b10000 ?
b110111 1
1'
#3670000
0'
#3675000
b111000 1
b10001 ?
1'
#3680000
0'
#3685000
b10010 ?
b111001 1
1'
#3690000
0'
#3695000
b111010 1
b10011 ?
1'
#3700000
0'
#3705000
b10100 ?
b111011 1
1'
#3710000
0'
#3715000
b111100 1
b10101 ?
1'
#3720000
0'
#3725000
b10110 ?
b111101 1
1'
#3730000
0'
#3735000
b111110 1
b10111 ?
1'
#3740000
0'
#3745000
b11000 ?
b111111 1
1'
#3750000
0'
#3755000
b1000000 1
b11001 ?
1'
#3760000
0'
#3765000
b11010 ?
b1000001 1
1'
#3770000
0'
#3775000
b1000010 1
b11011 ?
1'
#3780000
0'
#3785000
b11100 ?
b1000011 1
1'
#3790000
0'
#3795000
b1000100 1
b11101 ?
1'
#3800000
0'
#3805000
b11110 ?
b1000101 1
1'
#3810000
0'
#3815000
b1000110 1
b11111 ?
1'
#3820000
0'
#3825000
b100000 ?
b1000111 1
1'
#3830000
0'
#3835000
b1001000 1
b100001 ?
1'
#3840000
0'
#3845000
b100010 ?
b1001001 1
1'
#3850000
0'
#3855000
b1001010 1
b100011 ?
1'
#3860000
0'
#3865000
b100100 ?
b1001011 1
1'
#3870000
0'
#3875000
b1001100 1
b100101 ?
1'
#3880000
0'
#3885000
b100110 ?
b1001101 1
1'
#3890000
0'
#3895000
b1001110 1
b100111 ?
1'
#3900000
0'
#3905000
b101000 ?
b1001111 1
1'
#3910000
0'
